dbxio/__init__.py
dbxio/blobs/__init__.py
dbxio/blobs/block_upload.py
dbxio/blobs/download.py
dbxio/blobs/parquet.py
dbxio/core/__init__.py
dbxio/core/auth.py
dbxio/core/client.py
dbxio/core/cloud/__init__.py
dbxio/core/cloud/aws/__init__.py
dbxio/core/cloud/aws/object_storage.py
dbxio/core/cloud/azure/__init__.py
dbxio/core/cloud/azure/object_storage.py
dbxio/core/cloud/client/__init__.py
dbxio/core/cloud/client/object_storage.py
dbxio/core/cloud/exceptions.py
dbxio/core/cloud/gcp/__init__.py
dbxio/core/cloud/gcp/object_storage.py
dbxio/core/credentials.py
dbxio/core/exceptions.py
dbxio/core/settings.py
dbxio/delta/__init__.py
dbxio/delta/parsers.py
dbxio/delta/table.py
dbxio/delta/table_commands.py
dbxio/delta/table_schema.py
dbxio/sql/__init__.py
dbxio/sql/query.py
dbxio/sql/results.py
dbxio/sql/sql_driver.py
dbxio/sql/types.py
dbxio/utils/__init__.py
dbxio/utils/blobs.py
dbxio/utils/databricks.py
dbxio/utils/env.py
dbxio/utils/http.py
dbxio/utils/logging.py
dbxio/utils/retries.py
dbxio/volume/__init__.py
dbxio/volume/volume_commands.py
dbxio-0.5.3.dist-info/LICENSE
dbxio-0.5.3.dist-info/METADATA
dbxio-0.5.3.dist-info/WHEEL
dbxio-0.5.3.dist-info/RECORD
