Metadata-Version: 2.1
Name: dbxio
Version: 0.5.3
Summary: High-level Databricks client
Home-page: https://github.com/Toloka/dbxio
License: Apache-2.0
Keywords: python,databricks,dbx
Author: Nikita Yurasov
Author-email: nikitayurasov@toloka.ai
Requires-Python: >=3.9,<4.0
Classifier: License :: OSI Approved :: Apache Software License
Classifier: Programming Language :: Python :: 3
Classifier: Programming Language :: Python :: 3.9
Classifier: Programming Language :: Python :: 3.10
Classifier: Programming Language :: Python :: 3.11
Classifier: Programming Language :: Python :: 3.12
Classifier: Programming Language :: Python :: 3.13
Requires-Dist: attrs (>=23.2,<24.0)
Requires-Dist: azure-storage-blob (>=12.16,<13.0)
Requires-Dist: azure_core (>=1.26,<2.0)
Requires-Dist: azure_identity (>=1.13,<2.0)
Requires-Dist: cachetools (>=5.3,<6.0)
Requires-Dist: databricks-sdk (>=0.28,<0.29)
Requires-Dist: databricks-sql-connector (>=2.0)
Requires-Dist: decorator (>=5.1.1,<6.0.0)
Requires-Dist: jinja2 (>=3.1.3,<4.0.0)
Requires-Dist: numpy (>=1.23,<2.0)
Requires-Dist: pandas (<2.2.0)
Requires-Dist: pyarrow (>=14.0.1,<15.0.0)
Requires-Dist: pydantic (>=1.10,<3.0.0)
Requires-Dist: python-dateutil (>=2.8,<3.0)
Requires-Dist: tenacity (>=7.0.0)
Requires-Dist: urllib3 (>=1.0)
Project-URL: Documentation, https://github.com/Toloka/dbxio/blob/main/docs/README.md
Project-URL: Repository, https://github.com/Toloka/dbxio
